udev_monitor/__init__.py
udev_monitor/__main__.py
udev_monitor-1.3.0.dist-info/LICENSE
udev_monitor-1.3.0.dist-info/METADATA
udev_monitor-1.3.0.dist-info/WHEEL
udev_monitor-1.3.0.dist-info/entry_points.txt
udev_monitor-1.3.0.dist-info/top_level.txt
udev_monitor-1.3.0.dist-info/RECORD
