Metadata-Version: 2.1
Name: udev-monitor
Version: 1.3.0
Summary: Monitor udev events like usb devices being connected, and execute actions upon event
Home-page: https://github.com/netinvent/udev_monitor
Author: NetInvent - Orsiris de Jong
Author-email: contact@netinvent.fr
License: BSD
Keywords: shell,udev,usb,event,connect,plugged,plug and pray
Classifier: Development Status :: 5 - Production/Stable
Classifier: Intended Audience :: Developers
Classifier: Topic :: Software Development
Classifier: Topic :: System
Classifier: Topic :: System :: Operating System
Classifier: Topic :: System :: Shells
Classifier: Programming Language :: Python
Classifier: Programming Language :: Python :: 3
Classifier: Programming Language :: Python :: Implementation :: CPython
Classifier: Programming Language :: Python :: Implementation :: PyPy
Classifier: Operating System :: POSIX :: Linux
Classifier: License :: OSI Approved :: BSD License
Requires-Python: >=3.6
License-File: LICENSE
Requires-Dist: command-runner (>=1.4.0)
Requires-Dist: pyudev
Requires-Dist: ofunctions.threading (>=1.1.0)
Requires-Dist: ofunctions.logger-utils (>=2.3.0)
